<?xml version="1.0" encoding="UTF-8"?>
<objects serializationModel="Studio.02.02.00">
	<object class="AudioFile" id="{9b0a94b4-06ab-414e-a5a2-ec6aeef61fed}">
		<property name="assetPath">
			<value>ambience/bbc_bird_birdsong_forest_ambience-002.wav</value>
		</property>
		<property name="frequencyInKHz">
			<value>44.0999985</value>
		</property>
		<property name="channelCount">
			<value>2</value>
		</property>
		<property name="length">
			<value>0.87816326530612243</value>
		</property>
		<relationship name="masterAssetFolder">
			<destination>{7fd1a718-3a0f-4e47-9fc7-60eed5bc700e}</destination>
		</relationship>
	</object>
</objects>
